plotting_backends/__init__.py
plotting_backends/_version.py
plotting_backends/_version.pyi
plotting_backends/py.typed
plotting_backends-0.1.0.dist-info/METADATA
plotting_backends-0.1.0.dist-info/WHEEL
plotting_backends-0.1.0.dist-info/licenses/LICENSE
plotting_backends-0.1.0.dist-info/RECORD
