Metadata-Version: 2.3
Name: plotting_backends
Version: 0.1.0
Summary: Plotting dispatch backends
Project-URL: Homepage, https://github.com/GalacticDynamics/plotting_backends
Project-URL: Bug Tracker, https://github.com/GalacticDynamics/plotting_backends/issues
Project-URL: Changelog, https://github.com/GalacticDynamics/plotting_backends/releases
Author-email: galax maintainers <nstarkman@users.noreply.github.com>, Nathaniel Starkman <nstarman@users.noreply.github.com>
License: Copyright 2024 galax maintainers
License-File: LICENSE
Classifier: Development Status :: 1 - Planning
Classifier: Intended Audience :: Developers
Classifier: Intended Audience :: Science/Research
Classifier: License :: OSI Approved :: MIT License
Classifier: Operating System :: OS Independent
Classifier: Programming Language :: Python
Classifier: Programming Language :: Python :: 3
Classifier: Programming Language :: Python :: 3 :: Only
Classifier: Programming Language :: Python :: 3.8
Classifier: Programming Language :: Python :: 3.9
Classifier: Programming Language :: Python :: 3.10
Classifier: Programming Language :: Python :: 3.11
Classifier: Programming Language :: Python :: 3.12
Classifier: Programming Language :: Python :: 3.13
Classifier: Topic :: Scientific/Engineering
Classifier: Typing :: Typed
Requires-Python: >=3.8
Provides-Extra: dev
Requires-Dist: pytest-cov>=3; extra == 'dev'
Requires-Dist: pytest>=6; extra == 'dev'
Requires-Dist: sybil!=7.1.0; extra == 'dev'
Provides-Extra: test
Requires-Dist: pytest-cov>=3; extra == 'test'
Requires-Dist: pytest>=6; extra == 'test'
Requires-Dist: sybil!=7.1.0; extra == 'test'
